bake/__init__.py
bake/bakebook/__init__.py
bake/bakebook/bakebook.py
bake/bakebook/decorator.py
bake/bakebook/get.py
bake/cli/__init__.py
bake/cli/bake/__init__.py
bake/cli/bake/__main__.py
bake/cli/bake/main.py
bake/cli/bake/reinvocation.py
bake/cli/bakefile/__init__.py
bake/cli/bakefile/__main__.py
bake/cli/bakefile/add_inline.py
bake/cli/bakefile/export.py
bake/cli/bakefile/find_python.py
bake/cli/bakefile/init.py
bake/cli/bakefile/lint.py
bake/cli/bakefile/main.py
bake/cli/bakefile/uv.py
bake/cli/common/__init__.py
bake/cli/common/app.py
bake/cli/common/callback.py
bake/cli/common/context.py
bake/cli/common/exception_handler.py
bake/cli/common/obj.py
bake/cli/common/params.py
bake/cli/utils/__init__.py
bake/cli/utils/version.py
bake/manage/__init__.py
bake/manage/add_inline.py
bake/manage/find_python.py
bake/manage/lint.py
bake/manage/run_uv.py
bake/manage/write_bakefile.py
bake/py.typed
bake/samples/__init__.py
bake/samples/simple.py
bake/ui/__init__.py
bake/ui/console.py
bake/ui/logger/__init__.py
bake/ui/logger/capsys.py
bake/ui/logger/setup.py
bake/ui/logger/utils.py
bake/ui/params.py
bake/ui/run/__init__.py
bake/ui/run/run.py
bake/ui/run/script.py
bake/ui/run/splitter.py
bake/ui/run/uv.py
bake/ui/style.py
bake/utils/__init__.py
bake/utils/constants.py
bake/utils/env.py
bake/utils/exceptions.py
bakelib/__init__.py
bakelib/environ/__init__.py
bakelib/environ/bakebook.py
bakelib/environ/base.py
bakelib/environ/get_bakebook.py
bakelib/environ/presets.py
bakelib/space/__init__.py
bakelib/space/base.py
bakelib/space/python.py
bakelib/space/utils.py
bakefile-0.0.10.dist-info/WHEEL
bakefile-0.0.10.dist-info/entry_points.txt
bakefile-0.0.10.dist-info/METADATA
bakefile-0.0.10.dist-info/RECORD
