Metadata-Version: 2.3
Name: bakefile
Version: 0.0.10
Summary: Add your description here
Author: Wisaroot Lertthaweedech
Author-email: Wisaroot Lertthaweedech <l.wisaroot@gmail.com>
Requires-Dist: beautysh>=6.4.2
Requires-Dist: click>=8.3.1
Requires-Dist: loguru>=0.7.3
Requires-Dist: orjson>=3.11.5
Requires-Dist: pydantic-settings>=2.0.0
Requires-Dist: pydantic>=2.12.5
Requires-Dist: python-dotenv>=1.2.1
Requires-Dist: pyyaml>=6.0.3
Requires-Dist: rich>=14.2.0
Requires-Dist: ruff>=0.14.10
Requires-Dist: tomli>=2.0.0 ; python_full_version < '3.11'
Requires-Dist: ty>=0.0.8
Requires-Dist: typer>=0.21.0
Requires-Dist: uv>=0.9.20
Requires-Dist: pathspec>=1.0.3 ; extra == 'lib'
Requires-Python: >=3.10
Provides-Extra: lib
